{
    "name": "photos",
    "type": "page",
    "css": ["./css/photos.css"],
    "content":[
        {
            "name": "titlewpara",
            "vars": {
                "_twp_template_title": "$photographyworks$",
                "_twp_template_paragraph": [
                    "$photoscopyright$"
                ]
            }
        },
        {
            "name": "titlewdiv",
            "vars": {
                "_twd_template_title": ["$planespotting$"],
                "_twd_template_paragraph": [
                    {
                        "name": "picwithexif", 
                        "vars": {
                            "_pwexif_template_id": "N24927-1",
                            "_pwexif_template_src": "./imgs/photos/N24927-1.jpg",
                            "_pwexif_template_title": "N24927",
                            "_pwexif_template_description": "$N24927-1description$"
                        }
                    },
                    {
                        "name": "picwithexif", 
                        "vars": {
                            "_pwexif_template_id": "N174UP-1",
                            "_pwexif_template_src": "./imgs/photos/N174UP-1.jpg",
                            "_pwexif_template_title": "N174UP",
                            "_pwexif_template_description": "$N174UP-1description$"
                        }
                    }
                ]
            }
        },
        {
            "name": "titlewdiv",
            "vars": {
                "_twd_template_title": ["$travelphotos$"],
                "_twd_template_paragraph": [
                    {
                        "name": "picwithexif", 
                        "vars": {
                            "_pwexif_template_id": "greenlakebonfire",
                            "_pwexif_template_src": "./imgs/photos/greenlakebonfire.jpg",
                            "_pwexif_template_title": "Bonfire at Green Lake",
                            "_pwexif_template_description": "$greenlakebonfiredescription$"
                        }
                    },
                    {
                        "name": "picwithexif", 
                        "vars": {
                            "_pwexif_template_id": "greenlakestars1",
                            "_pwexif_template_src": "./imgs/photos/greenlakestars1.jpg",
                            "_pwexif_template_title": "greenlakestars1",
                            "_pwexif_template_description": "$greenlakestars1description$"
                        }
                    },
                    {
                        "name": "picwithexif", 
                        "vars": {
                            "_pwexif_template_id": "greenlakestars2",
                            "_pwexif_template_src": "./imgs/photos/greenlakestars2.jpg",
                            "_pwexif_template_title": "greenlakestars2",
                            "_pwexif_template_description": "$greenlakestars2description$"
                        }
                    }
                ]
            }
        }
    ]
}
