{
    "name": "teaching",
    "type": "page",
    "content":[
        {
            "name": "titlewdiv",
            "vars": {
                "_twd_template_title": "$teaching$",
                "_twd_template_paragraph": [
                    {
                        "name": "titlewpara",
                        "vars": {
                            "_twp_template_title": "$foreword$",
                            "_twp_template_paragraph": [
                                "$teachingforewordcontent$"
                            ],
                            "_twp_template_titletype": "h4",
                            "_twp_template_align": "left",
                            "_twp_template_maxwidth": "80%"
                        }
                    }
                ],
                "_twd_template_align": "left",
                "_twd_template_maxwidth": "80%"
            }
        }
    ]
}
